acpype/__init__.py
acpype/acs_api.py
acpype/amber_linux/GNU_LGPL_v3
acpype/amber_linux/LICENSE
acpype/amber_linux/amber.sh
acpype/amber_linux/bin/am1bcc
acpype/amber_linux/bin/antechamber
acpype/amber_linux/bin/atomtype
acpype/amber_linux/bin/bondtype
acpype/amber_linux/bin/charmmgen
acpype/amber_linux/bin/parmchk2
acpype/amber_linux/bin/sqm
acpype/amber_linux/bin/teLeap
acpype/amber_linux/bin/tleap
acpype/amber_linux/bin/wrapped_progs/am1bcc
acpype/amber_linux/bin/wrapped_progs/antechamber
acpype/amber_linux/bin/wrapped_progs/atomtype
acpype/amber_linux/bin/wrapped_progs/bondtype
acpype/amber_linux/bin/wrapped_progs/parmchk2
acpype/amber_linux/dat/antechamber/APS.DAT
acpype/amber_linux/dat/antechamber/ATCOR.DAT
acpype/amber_linux/dat/antechamber/ATOMTYPE_AMBER.DEF
acpype/amber_linux/dat/antechamber/ATOMTYPE_BCC.DEF
acpype/amber_linux/dat/antechamber/ATOMTYPE_CHECK.TAB
acpype/amber_linux/dat/antechamber/ATOMTYPE_GAS.DEF
acpype/amber_linux/dat/antechamber/ATOMTYPE_GFF.DEF
acpype/amber_linux/dat/antechamber/ATOMTYPE_GFF2.DEF
acpype/amber_linux/dat/antechamber/ATOMTYPE_SYBYL.DEF
acpype/amber_linux/dat/antechamber/ATOM_EQU.TYPE
acpype/amber_linux/dat/antechamber/BCCPARM.DAT
acpype/amber_linux/dat/antechamber/BONDTYPE_CHECK.TAB
acpype/amber_linux/dat/antechamber/CONNECT.TPL
acpype/amber_linux/dat/antechamber/CORR_NAME_TYPE.DAT
acpype/amber_linux/dat/antechamber/ESPPARM.DAT
acpype/amber_linux/dat/antechamber/GASPARM.DAT
acpype/amber_linux/dat/antechamber/PARMCHK.DAT
acpype/amber_linux/dat/antechamber/PARM_BLBA_GAFF.DAT
acpype/amber_linux/dat/antechamber/PARM_BLBA_GAFF2.DAT
acpype/amber_linux/dat/antechamber/RADIUS.DAT
acpype/amber_linux/dat/antechamber/database_sample.def
acpype/amber_linux/dat/antechamber/mainchain_sample.dat
acpype/amber_linux/dat/antechamber/residuegen_sample.dat
acpype/amber_linux/dat/antechamber/respgen_addfile_sample.dat
acpype/amber_linux/dat/chamber/par_all22_prot.inp
acpype/amber_linux/dat/chamber/par_all22_sugar.inp
acpype-2023.10.27.dist-info/LICENSE
acpype-2023.10.27.dist-info/METADATA
acpype-2023.10.27.dist-info/WHEEL
acpype-2023.10.27.dist-info/entry_points.txt
acpype-2023.10.27.dist-info/RECORD
