Metadata-Version: 2.1
Name: acpype
Version: 2023.10.27
Summary: ACPYPE - AnteChamber PYthon Parser interfacE
Home-page: https://alanwilter.github.io/acpype/
License: GPL-3.0-or-later
Keywords: acpype,amber,gromacs
Author: Alan Silva
Author-email: alanwilter@gmail.com
Requires-Python: >=3.8,<4.0
Classifier: Intended Audience :: Science/Research
Classifier: License :: OSI Approved :: GNU General Public License v3 or later (GPLv3+)
Classifier: Natural Language :: English
Classifier: Programming Language :: Python :: 3
Classifier: Programming Language :: Python :: 3.8
Classifier: Programming Language :: Python :: 3.9
Classifier: Programming Language :: Python :: 3.10
Classifier: Programming Language :: Python :: 3.11
Classifier: Topic :: Scientific/Engineering :: Bio-Informatics
Requires-Dist: openbabel-wheel (>=3.1.1.19,<4.0.0.0)
Project-URL: Bug Tracker, https://github.com/alanwilter/acpype/issues
Project-URL: Docs, https://acpype.readthedocs.io
Project-URL: DOI, https://doi.org/10.1186/1756-0500-5-367
Project-URL: Repository, https://github.com/alanwilter/acpype
Project-URL: Wiki, https://github.com/alanwilter/acpype/wiki
